{
  "date": "January 25",
  "events": [
    {
      "year": 1924,
      "title": "First Winter Olympics Open in Chamonix, France",
      "description": "The first Winter Olympic Games officially began in Chamonix, marking the start of international competition in winter sports under the Olympic banner.",
      "category": "Sports",
      "significance": "It established the Winter Olympics as a major international sporting event, promoting winter sports worldwide."
    },
    {
      "year": 1949,
      "title": "Israel Becomes a Member of the United Nations",
      "description": "The United Nations General Assembly voted to admit the newly established State of Israel as the 59th member of the UN.",
      "category": "Politics",
      "significance": "This recognition was crucial for the legitimacy and international acceptance of Israel as a sovereign state."
    },
    {
      "year": 1915,
      "title": "Dmitri Shostakovich Born",
      "description": "Russian composer Dmitri Shostakovich, renowned for his symphonies and chamber music, was born in Saint Petersburg.",
      "category": "Births",
      "significance": "He became one of the major composers of the 20th century, with works that reflected the complexities of Soviet life."
    },
    {
      "year": 2011,
      "title": "The Egyptian Revolution: Mass Protests Begin",
      "description": "Millions of Egyptians took to the streets of Cairo to demand the resignation of President Hosni Mubarak, marking a pivotal moment in the Arab Spring.",
      "category": "Politics",
      "significance": "It led to Mubarak's resignation and significant political change in Egypt, inspiring other uprisings in the region."
    }
  ]
}