{
  "date": "February 16",
  "events": [
    {
      "year": 1923,
      "title": "Discovery of King Tutankhamun's Tomb Announced",
      "description": "Howard Carter announced the discovery of the tomb of Pharaoh Tutankhamun in the Valley of the Kings, one of the most significant archaeological finds in Egyptology.",
      "category": "Archaeology",
      "significance": "Provided invaluable insight into ancient Egyptian culture and history, sparking worldwide interest in Egyptology."
    },
    {
      "year": 1959,
      "title": "Fidel Castro Becomes Prime Minister of Cuba",
      "description": "Fidel Castro formally assumed the position of Prime Minister of Cuba, consolidating power after the Cuban Revolution.",
      "category": "Politics",
      "significance": "Marked the beginning of Castro's long-term leadership and the establishment of a communist government in Cuba."
    },
    {
      "year": 1918,
      "title": "Lithuania Declares Independence from Russia",
      "description": "Lithuania officially declared its independence, establishing itself as a sovereign state after centuries of foreign rule.",
      "category": "Nationalism/Independence",
      "significance": "Signaled the re-establishment of Lithuania as an independent nation-state following World War I."
    },
    {
      "year": 1804,
      "title": "Napoleon Bonaparte Declares Himself Emperor of the French",
      "description": "Napoleon crowned himself Emperor in a ceremony symbolizing the peak of his power during the French Empire.",
      "category": "Political History",
      "significance": "Marked the transition of France from republic to empire, significantly impacting European politics and wars."
    },
    {
      "year": 1937,
      "title": "Snow White and the Seven Dwarfs Premieres",
      "description": "Walt Disney's 'Snow White and the Seven Dwarfs,' the first full-length animated feature film, premiered in Hollywood.",
      "category": "Culture/Entertainment",
      "significance": "Revolutionized animation and cinema, establishing feature-length animated films as a viable genre."
    }
  ]
}